a2a_universal/__init__.py
a2a_universal/__main__.py
a2a_universal/app.py
a2a_universal/card.py
a2a_universal/cli.py
a2a_universal/client.py
a2a_universal/config.py
a2a_universal/frameworks.py
a2a_universal/logging_config.py
a2a_universal/models.py
a2a_universal/provider_api.py
a2a_universal/providers.py
a2a_universal/py.typed
a2a_universal/runner.py
a2a_universal/server.py
a2a_universal/validators.py
a2a_universal/verification.py
a2a_universal/adapters/autogen_tool.py
a2a_universal/adapters/bee_tool.py
a2a_universal/adapters/beeai_agent.py
a2a_universal/adapters/crewai_base_tool.py
a2a_universal/adapters/crewai_tool.py
a2a_universal/adapters/langchain_tool.py
a2a_universal/adapters/langgraph_agent.py
a2a_universal/adapters/langgraph_node.py
a2a_universal/adapters/private_adapter.py
a2a_universal/framework_plugins/__init__.py
a2a_universal/framework_plugins/beeai.py
a2a_universal/framework_plugins/crewai.py
a2a_universal/framework_plugins/langgraph.py
a2a_universal/framework_plugins/native.py
a2a_universal/provider_plugins/__init__.py
a2a_universal/provider_plugins/anthropic.py
a2a_universal/provider_plugins/azure_openai.py
a2a_universal/provider_plugins/bedrock.py
a2a_universal/provider_plugins/echo.py
a2a_universal/provider_plugins/gemini.py
a2a_universal/provider_plugins/ollama.py
a2a_universal/provider_plugins/openai.py
a2a_universal/provider_plugins/watsonx.py
universal_a2a_agent-0.1.2.dist-info/licenses/LICENSE
universal_a2a_agent-0.1.2.dist-info/METADATA
universal_a2a_agent-0.1.2.dist-info/WHEEL
universal_a2a_agent-0.1.2.dist-info/entry_points.txt
universal_a2a_agent-0.1.2.dist-info/top_level.txt
universal_a2a_agent-0.1.2.dist-info/RECORD
