Metadata-Version: 2.4
Name: universal-a2a-agent
Version: 0.1.2
Summary: Framework-agnostic A2A agent with pluggable Providers & Frameworks (MCP, LangChain, LangGraph, CrewAI, BeeAI, AutoGen, watsonx.ai)
Author-email: Ruslan Magana Vsevolodovna <contact@ruslanmv.com>
License: Apache-2.0
Requires-Python: >=3.9
License-File: LICENSE
Requires-Dist: fastapi>=0.111
Requires-Dist: uvicorn>=0.30
Requires-Dist: pydantic>=2.6
Requires-Dist: httpx>=0.27
Requires-Dist: pydantic-settings>=2.3
Requires-Dist: typer>=0.12
Requires-Dist: python-dotenv>=1.0
Provides-Extra: langchain
Requires-Dist: langchain>=0.2; extra == "langchain"
Requires-Dist: langchain-community>=0.2; extra == "langchain"
Provides-Extra: langgraph
Requires-Dist: langgraph>=0.2; extra == "langgraph"
Requires-Dist: langchain-core>=0.2; extra == "langgraph"
Requires-Dist: langchain>=0.2; extra == "langgraph"
Requires-Dist: langchain-community>=0.2; extra == "langgraph"
Provides-Extra: crewai
Requires-Dist: crewai>=0.51; extra == "crewai"
Requires-Dist: crewai-tools>=0.1.0; extra == "crewai"
Provides-Extra: autogen
Requires-Dist: pyautogen>=0.2; extra == "autogen"
Provides-Extra: beeai
Requires-Dist: beeai-framework[a2a]>=0.1.44; extra == "beeai"
Provides-Extra: openai
Requires-Dist: openai>=1.0; extra == "openai"
Provides-Extra: watsonx
Requires-Dist: ibm-watsonx-ai>=1.1.15; extra == "watsonx"
Provides-Extra: anthropic
Requires-Dist: anthropic>=0.30; extra == "anthropic"
Provides-Extra: gemini
Requires-Dist: google-generativeai>=0.7; extra == "gemini"
Provides-Extra: azure-openai
Requires-Dist: openai>=1.0; extra == "azure-openai"
Provides-Extra: bedrock
Requires-Dist: boto3>=1.34; extra == "bedrock"
Requires-Dist: botocore>=1.34; extra == "bedrock"
Provides-Extra: ollama
Provides-Extra: providers-all
Requires-Dist: openai>=1.0; extra == "providers-all"
Requires-Dist: ibm-watsonx-ai>=1.0; extra == "providers-all"
Requires-Dist: anthropic>=0.30; extra == "providers-all"
Requires-Dist: google-generativeai>=0.7; extra == "providers-all"
Requires-Dist: boto3>=1.34; extra == "providers-all"
Requires-Dist: botocore>=1.34; extra == "providers-all"
Provides-Extra: frameworks-all
Requires-Dist: langgraph>=0.2; extra == "frameworks-all"
Requires-Dist: langchain-core>=0.2; extra == "frameworks-all"
Requires-Dist: langchain>=0.2; extra == "frameworks-all"
Requires-Dist: langchain-community>=0.2; extra == "frameworks-all"
Requires-Dist: crewai>=0.51; extra == "frameworks-all"
Requires-Dist: crewai-tools>=0.1.0; extra == "frameworks-all"
Requires-Dist: pyautogen>=0.2; extra == "frameworks-all"
Requires-Dist: beeai-framework[a2a]>=0.1.44; extra == "frameworks-all"
Provides-Extra: all
Requires-Dist: langgraph>=0.2; extra == "all"
Requires-Dist: langchain-core>=0.2; extra == "all"
Requires-Dist: langchain>=0.2; extra == "all"
Requires-Dist: langchain-community>=0.2; extra == "all"
Requires-Dist: crewai>=0.51; extra == "all"
Requires-Dist: crewai-tools>=0.1.0; extra == "all"
Requires-Dist: pyautogen>=0.2; extra == "all"
Requires-Dist: beeai-framework[a2a]>=0.1.44; extra == "all"
Requires-Dist: openai>=1.0; extra == "all"
Requires-Dist: ibm-watsonx-ai>=1.0; extra == "all"
Requires-Dist: anthropic>=0.30; extra == "all"
Requires-Dist: google-generativeai>=0.7; extra == "all"
Requires-Dist: boto3>=1.34; extra == "all"
Requires-Dist: botocore>=1.34; extra == "all"
Dynamic: license-file
